{"timestamp":"2018-04-14T00:58:00.019+05:30","filter":[{"name":"countries","label":"Countries","country":[{"code":"bj","count":"2","#text":"Benin"},{"code":"et","count":"3","#text":"Ethiopia"},{"code":"mg","count":"2","#text":"Madagascar"},{"code":"mu","count":"148","#text":"Mauritius"},{"code":"ng","count":"1","#text":"Nigeria"},{"code":"tg","count":"44","#text":"Togo"}]},{"name":"langs","label":"Languages","lang":[{"code":"eng","count":"151","#text":"English"},{"code":"fra","count":"46","#text":"Français"},{"code":"mul","count":"3","#text":"Multilingual"}]},{"name":"years","label":"Years","year":[{"year":"2016","count":"18"},{"year":"2015","count":"2"},{"year":"2014","count":"1"},{"year":"2013","count":"5"},{"year":"2012","count":"3"},{"year":"2011","count":"5"},{"year":"2010","count":"4"},{"year":"2009","count":"6"},{"year":"2008","count":"2"},{"year":"2007","count":"7"},{"year":"2006","count":"3"},{"year":"2005","count":"5"},{"year":"2004","count":"4"},{"year":"2003","count":"4"},{"year":"2002","count":"3"},{"year":"2001","count":"1"},{"year":"2000","count":"7"},{"year":"1999","count":"3"},{"year":"1998","count":"2"},{"year":"1997","count":"1"},{"year":"1996","count":"1"},{"year":"1995","count":"3"},{"year":"1994","count":"4"},{"year":"1991","count":"1"},{"year":"1990","count":"4"},{"year":"1989","count":"2"},{"year":"1988","count":"2"},{"year":"1985","count":"1"},{"year":"1984","count":"1"},{"year":"1983","count":"1"},{"year":"1981","count":"2"},{"year":"1980","count":"3"},{"year":"1979","count":"2"},{"year":"1978","count":"3"},{"year":"1977","count":"1"},{"year":"1976","count":"3"},{"year":"1975","count":"2"},{"year":"1974","count":"1"},{"year":"1972","count":"3"},{"year":"1971","count":"2"},{"year":"1970","count":"3"},{"year":"1969","count":"2"},{"year":"1968","count":"2"},{"year":"1966","count":"6"},{"year":"1964","count":"2"},{"year":"1962","count":"3"},{"year":"1961","count":"3"},{"year":"1960","count":"1"},{"year":"1958","count":"1"},{"year":"1956","count":"1"},{"year":"1955","count":"1"},{"year":"1954","count":"2"},{"year":"1953","count":"3"},{"year":"1952","count":"2"},{"year":"1951","count":"2"},{"year":"1950","count":"4"},{"year":"1949","count":"4"},{"year":"1948","count":"5"},{"year":"1944","count":"3"},{"year":"1943","count":"1"},{"year":"1942","count":"2"},{"year":"1941","count":"1"},{"year":"1940","count":"3"},{"year":"1939","count":"2"},{"year":"1938","count":"1"},{"year":"1935","count":"1"},{"year":"1934","count":"2"},{"year":"1933","count":"1"},{"year":"1932","count":"2"},{"year":"1931","count":"1"},{"year":"1930","count":"2"},{"year":"1929","count":"1"},{"year":"1923","count":"1"},{"year":"1919","count":"1"}]},{"name":"keywords","label":"Subjects","keyword":[{"value":"Accord","count":"2","showAs":"Accord"},{"value":"Acquisition","count":"1","showAs":"Acquisition"},{"value":"Act","count":"63","showAs":"Act"},{"value":"Activités","count":"1","showAs":"Activités"},{"value":"Administration","count":"8","showAs":"Administration"},{"value":"Administrative","count":"1","showAs":"Administrative"},{"value":"AdministrativeLaw","count":"1","showAs":"Administrative Law"},{"value":"Admission","count":"1","showAs":"Admission"},{"value":"AffairesSociales","count":"1","showAs":"Affaires Sociales"},{"value":"AffairesÉtrangers","count":"1","showAs":"Affaires étrangers"},{"value":"AgenceÉconomique","count":"1","showAs":"Agence économique"},{"value":"Agency","count":"1","showAs":"Agency"},{"value":"Agent","count":"3","showAs":"Agent"},{"value":"Agreement","count":"5","showAs":"Agreement"},{"value":"Agriculture","count":"3","showAs":"Agriculture"},{"value":"Agrément","count":"1","showAs":"Agrément"},{"value":"Aircraft","count":"1","showAs":"Aircraft"},{"value":"Airline","count":"1","showAs":"Airline"},{"value":"Airport","count":"2","showAs":"Airport"},{"value":"Allocations","count":"2","showAs":"Allocations"},{"value":"Allowable","count":"1","showAs":"Allowable"},{"value":"Allowances","count":"1","showAs":"Allowances"},{"value":"Amend","count":"1","showAs":"Amend"},{"value":"Amendment","count":"28","showAs":"Amendment"},{"value":"Amends","count":"1","showAs":"Amends"},{"value":"Annulation","count":"1","showAs":"Annulation"},{"value":"Antibiotics","count":"1","showAs":"Antibiotics"},{"value":"Appeal","count":"1","showAs":"Appeal"},{"value":"Applicant","count":"1","showAs":"Applicant"},{"value":"Application","count":"3","showAs":"Application"},{"value":"Approbation","count":"1","showAs":"Approbation"},{"value":"Appropriation","count":"1","showAs":"Appropriation"},{"value":"Armée","count":"1","showAs":"Armée"},{"value":"Assessment","count":"1","showAs":"Assessment"},{"value":"Assessor","count":"1","showAs":"Assessor"},{"value":"Assimilation","count":"2","showAs":"Assimilation"},{"value":"Association","count":"2","showAs":"Association"},{"value":"Athletes","count":"1","showAs":"Athletes"},{"value":"Audit","count":"2","showAs":"Audit"},{"value":"Auditor","count":"1","showAs":"Auditor"},{"value":"AuthorisedOfficer","count":"1","showAs":"Authorised officer"},{"value":"Authority","count":"1","showAs":"Authority"},{"value":"AutonomieFinanciere","count":"1","showAs":"Autonomie financiere"},{"value":"Autorisation","count":"2","showAs":"Autorisation"},{"value":"AviationCivile","count":"1","showAs":"Aviation civile"},{"value":"Aérodromes","count":"1","showAs":"Aérodromes"},{"value":"Bancaire","count":"1","showAs":"Bancaire"},{"value":"Banking","count":"3","showAs":"Banking"},{"value":"Bankruptcy","count":"1","showAs":"Bankruptcy"},{"value":"Baseline","count":"1","showAs":"Baseline"},{"value":"Bay","count":"1","showAs":"Bay"},{"value":"Bill","count":"1","showAs":"Bill"},{"value":"Board","count":"3","showAs":"Board"},{"value":"Booth","count":"1","showAs":"Booth"},{"value":"Borrower","count":"1","showAs":"Borrower"},{"value":"Bourse","count":"1","showAs":"Bourse"},{"value":"Broadcasting","count":"1","showAs":"Broadcasting"},{"value":"Budget","count":"4","showAs":"Budget"},{"value":"BudgetSuplémentaire","count":"1","showAs":"Budget suplémentaire"},{"value":"Budgets","count":"1","showAs":"Budgets"},{"value":"Buildings","count":"1","showAs":"Buildings"},{"value":"BureauDePostes","count":"1","showAs":"Bureau de postes"},{"value":"Business","count":"6","showAs":"Business"},{"value":"Buyers","count":"1","showAs":"Buyers"},{"value":"Bétail","count":"1","showAs":"Bétail"},{"value":"Cadres","count":"1","showAs":"Cadres"},{"value":"Calorifiques","count":"1","showAs":"Calorifiques"},{"value":"CampagneÉlectorale","count":"1","showAs":"Campagne électorale"},{"value":"Cancellation","count":"2","showAs":"Cancellation"},{"value":"Cancelled","count":"1","showAs":"Cancelled"},{"value":"Carrière","count":"1","showAs":"Carrière"},{"value":"Cash","count":"1","showAs":"Cash"},{"value":"Cemetery","count":"1","showAs":"Cemetery"},{"value":"Census","count":"2","showAs":"Census"},{"value":"CentralHousingAuthority","count":"1","showAs":"Central Housing Authority"},{"value":"Certificate","count":"2","showAs":"Certificate"},{"value":"Certification","count":"1","showAs":"Certification"},{"value":"Cessionnaire","count":"1","showAs":"Cessionnaire"},{"value":"ChambreDeCommerce","count":"1","showAs":"Chambre de commerce"},{"value":"Chargement","count":"1","showAs":"Chargement"},{"value":"Charges","count":"1","showAs":"Charges"},{"value":"Charter","count":"1","showAs":"Charter"},{"value":"ChemicalFertilizer","count":"1","showAs":"Chemical Fertilizer"},{"value":"CheminDeFer","count":"1","showAs":"Chemin de fer"},{"value":"CheminsDeFer","count":"1","showAs":"Chemins de fer"},{"value":"ChiefSurveyor","count":"1","showAs":"Chief Surveyor"},{"value":"ChildProtection","count":"1","showAs":"Child Protection"},{"value":"ChildTrafficking","count":"1","showAs":"Child trafficking"},{"value":"Children/Juveniles/Minors","count":"1","showAs":"Children / Juveniles / Minors"},{"value":"Circulation","count":"1","showAs":"Circulation"},{"value":"CivilAviation","count":"2","showAs":"Civil Aviation"},{"value":"CivilEstablishment","count":"2","showAs":"Civil Establishment"},{"value":"CivilSociety","count":"1","showAs":"Civil Society"},{"value":"Classement","count":"1","showAs":"Classement"},{"value":"ClauseCompromissoire","count":"1","showAs":"Clause compromissoire"},{"value":"Code","count":"1","showAs":"Code"},{"value":"Colony","count":"4","showAs":"Colony"},{"value":"Comité","count":"1","showAs":"Comité"},{"value":"Commander","count":"1","showAs":"Commander"},{"value":"Commence","count":"1","showAs":"Commence"},{"value":"Commencement","count":"1","showAs":"Commencement"},{"value":"Commerce","count":"8","showAs":"Commerce"},{"value":"Commerciale","count":"1","showAs":"Commerciale"},{"value":"Commission","count":"3","showAs":"Commission"},{"value":"CommissionNationale","count":"1","showAs":"Commission nationale"},{"value":"Commissioner","count":"1","showAs":"Commissioner"},{"value":"CommissionÉlectorale","count":"1","showAs":"Commission électorale"},{"value":"Committees","count":"1","showAs":"Committees"},{"value":"Commodities","count":"3","showAs":"Commodities"},{"value":"CommonGrave","count":"1","showAs":"Common Grave"},{"value":"Commonwealth","count":"1","showAs":"Commonwealth"},{"value":"Commune-mixte","count":"1","showAs":"Commune-mixte"},{"value":"Communiqué","count":"1","showAs":"Communiqué"},{"value":"CompagnieAutonome","count":"1","showAs":"Compagnie autonome"},{"value":"Company/Companies","count":"2","showAs":"Company / Companies"},{"value":"CompanyLaw/CorporateLaw","count":"1","showAs":"Company Law / Corporate Law"},{"value":"Competency","count":"1","showAs":"Competency"},{"value":"ComptableGestionnaire","count":"1","showAs":"Comptable gestionnaire"},{"value":"Concours","count":"3","showAs":"Concours"},{"value":"Conférences","count":"1","showAs":"Conférences"},{"value":"ConféreneceNationale","count":"1","showAs":"Conférenece nationale"},{"value":"Congregation","count":"1","showAs":"Congregation"},{"value":"Conseil","count":"1","showAs":"Conseil"},{"value":"Constituencies","count":"1","showAs":"Constituencies"},{"value":"Constituency","count":"1","showAs":"Constituency"},{"value":"Constitution","count":"3","showAs":"Constitution"},{"value":"Construction","count":"1","showAs":"Construction"},{"value":"Consultation","count":"1","showAs":"Consultation"},{"value":"Consumer","count":"6","showAs":"Consumer"},{"value":"Contrat","count":"1","showAs":"Contrat"},{"value":"Control","count":"7","showAs":"Control"},{"value":"Convention","count":"1","showAs":"Convention"},{"value":"Conviction","count":"1","showAs":"Conviction"},{"value":"Convocation","count":"1","showAs":"Convocation"},{"value":"Corpse","count":"1","showAs":"Corpse"},{"value":"CorpsÉlectoral","count":"1","showAs":"Corps électoral"},{"value":"Costs","count":"1","showAs":"Costs"},{"value":"Council","count":"14","showAs":"Council"},{"value":"CountryPlanning","count":"1","showAs":"Country Planning"},{"value":"CountryRepresentative","count":"1","showAs":"Country Representative"},{"value":"CourConstitutionnelle","count":"1","showAs":"Cour constitutionnelle"},{"value":"Court","count":"2","showAs":"Court"},{"value":"Credit","count":"1","showAs":"Credit"},{"value":"Cremation","count":"1","showAs":"Cremation"},{"value":"CriminalCode","count":"1","showAs":"Criminal Code"},{"value":"CriminalProcedure","count":"1","showAs":"Criminal Procedure"},{"value":"CropSeason","count":"1","showAs":"Crop Season"},{"value":"Création","count":"1","showAs":"Création"},{"value":"Crédits","count":"1","showAs":"Crédits"},{"value":"Cultivation","count":"1","showAs":"Cultivation"},{"value":"Custody","count":"1","showAs":"Custody"},{"value":"Customs","count":"2","showAs":"Customs"},{"value":"CustomsDuties","count":"1","showAs":"Customs duties"},{"value":"CustomsDuty","count":"1","showAs":"Customs Duty"},{"value":"CustomsTariff","count":"1","showAs":"Customs Tariff"},{"value":"Damages","count":"1","showAs":"Damages"},{"value":"DangerousChemicals","count":"1","showAs":"Dangerous Chemicals"},{"value":"Decision","count":"1","showAs":"Decision"},{"value":"Declaration","count":"3","showAs":"Declaration"},{"value":"Declare","count":"1","showAs":"Declare"},{"value":"Defence","count":"5","showAs":"Defence"},{"value":"Delegation","count":"1","showAs":"Delegation"},{"value":"DentalCouncil","count":"1","showAs":"Dental Council"},{"value":"Department","count":"2","showAs":"Department"},{"value":"Depaysement","count":"1","showAs":"Depaysement"},{"value":"Dependencies","count":"1","showAs":"Dependencies"},{"value":"Depense","count":"1","showAs":"Depense"},{"value":"Deportation","count":"1","showAs":"Deportation"},{"value":"Desengagement","count":"1","showAs":"Desengagement"},{"value":"Development","count":"4","showAs":"Development"},{"value":"DeveloppementEconomique","count":"1","showAs":"Developpement economique"},{"value":"DeveloppementIntellectual","count":"1","showAs":"Developpement intellectual"},{"value":"Disinfectants","count":"1","showAs":"Disinfectants"},{"value":"Dispensary","count":"1","showAs":"Dispensary"},{"value":"DisplacedPersons","count":"1","showAs":"Displaced Persons"},{"value":"Dispositions","count":"1","showAs":"Dispositions"},{"value":"Distribute","count":"1","showAs":"Distribute"},{"value":"Distribution","count":"1","showAs":"Distribution"},{"value":"Districts","count":"1","showAs":"Districts"},{"value":"Donation","count":"1","showAs":"Donation"},{"value":"Dossiers","count":"1","showAs":"Dossiers"},{"value":"Dotation","count":"1","showAs":"Dotation"},{"value":"Douanes","count":"2","showAs":"Douanes"},{"value":"Droits","count":"1","showAs":"Droits"},{"value":"Drugs","count":"1","showAs":"Drugs"},{"value":"Duty","count":"1","showAs":"Duty"},{"value":"Déliberation","count":"1","showAs":"Déliberation"},{"value":"Déliberations","count":"1","showAs":"Déliberations"},{"value":"Démission","count":"1","showAs":"Démission"},{"value":"Dénomination","count":"1","showAs":"Dénomination"},{"value":"Dépenses","count":"2","showAs":"Dépenses"},{"value":"Déplacement","count":"2","showAs":"Déplacement"},{"value":"Détache","count":"1","showAs":"Détache"},{"value":"Développement","count":"1","showAs":"Développement"},{"value":"Ecole","count":"1","showAs":"Ecole"},{"value":"EcoleNationale","count":"1","showAs":"Ecole nationale"},{"value":"Education","count":"2","showAs":"Education"},{"value":"Election","count":"1","showAs":"Election"},{"value":"Election/Elections","count":"3","showAs":"Election / Elections"},{"value":"ElectionPrésidentielle","count":"1","showAs":"Election Présidentielle"},{"value":"Electorale","count":"1","showAs":"Electorale"},{"value":"Electricity","count":"1","showAs":"Electricity"},{"value":"EmergencyLaws","count":"1","showAs":"Emergency Laws"},{"value":"Emoluments","count":"3","showAs":"Emoluments"},{"value":"Emplois","count":"1","showAs":"Emplois"},{"value":"Employee","count":"1","showAs":"Employee"},{"value":"Employment","count":"10","showAs":"Employment"},{"value":"EmploymentRelations","count":"1","showAs":"Employment Relations"},{"value":"Enregistration","count":"1","showAs":"Enregistration"},{"value":"Enseignants","count":"1","showAs":"Enseignants"},{"value":"Enseignement","count":"3","showAs":"Enseignement"},{"value":"EntrepreneurDeBâtiment","count":"1","showAs":"Entrepreneur de bâtiment"},{"value":"Entreprise","count":"1","showAs":"Entreprise"},{"value":"EntreprisesDeBâtiment","count":"1","showAs":"Entreprises de bâtiment"},{"value":"EntreprisesPubliques","count":"1","showAs":"Entreprises publiques"},{"value":"EnvironmentalLaw","count":"3","showAs":"Environmental Law"},{"value":"EnvironmentalProtection","count":"1","showAs":"Environmental Protection"},{"value":"Estate","count":"2","showAs":"Estate"},{"value":"Etablissement","count":"2","showAs":"Etablissement"},{"value":"EtudesD'animateurs","count":"1","showAs":"Etudes d'animateurs"},{"value":"Etudier","count":"1","showAs":"Etudier"},{"value":"Evidence","count":"2","showAs":"Evidence"},{"value":"Examinations","count":"1","showAs":"Examinations"},{"value":"Excellence","count":"1","showAs":"Excellence"},{"value":"Excellency","count":"1","showAs":"Excellency"},{"value":"Excise","count":"1","showAs":"Excise"},{"value":"Execution","count":"1","showAs":"Execution"},{"value":"ExecutiveCouncil","count":"1","showAs":"Executive council"},{"value":"Exercise","count":"1","showAs":"Exercise"},{"value":"Expenditure","count":"1","showAs":"Expenditure"},{"value":"Exploitation","count":"1","showAs":"Exploitation"},{"value":"ExportDuty","count":"1","showAs":"Export duty"},{"value":"Exportation","count":"1","showAs":"Exportation"},{"value":"Exportations","count":"1","showAs":"Exportations"},{"value":"Exports","count":"1","showAs":"Exports"},{"value":"Expression","count":"1","showAs":"Expression"},{"value":"Extension","count":"1","showAs":"Extension"},{"value":"Exécution","count":"1","showAs":"Exécution"},{"value":"FalseParticulars","count":"1","showAs":"False Particulars"},{"value":"FamilyLaw","count":"1","showAs":"Family Law"},{"value":"Fares","count":"2","showAs":"Fares"},{"value":"Federation","count":"1","showAs":"Federation"},{"value":"Fees","count":"3","showAs":"Fees"},{"value":"Finance","count":"9","showAs":"Finance"},{"value":"Finances","count":"3","showAs":"Finances"},{"value":"FinancialReportingAct","count":"1","showAs":"Financial Reporting Act"},{"value":"FinancialYear","count":"1","showAs":"Financial Year"},{"value":"Financières","count":"1","showAs":"Financières"},{"value":"Fishery/Fisheries","count":"1","showAs":"Fishery / Fisheries"},{"value":"Fonctionnaire","count":"1","showAs":"Fonctionnaire"},{"value":"Fonctionnaires","count":"2","showAs":"Fonctionnaires"},{"value":"Fonctionnement","count":"1","showAs":"Fonctionnement"},{"value":"Food","count":"2","showAs":"Food"},{"value":"Football","count":"1","showAs":"Football"},{"value":"Formation","count":"1","showAs":"Formation"},{"value":"Foundation","count":"1","showAs":"Foundation"},{"value":"FrozenMutton","count":"1","showAs":"Frozen Mutton"},{"value":"Fumigation","count":"1","showAs":"Fumigation"},{"value":"Functions","count":"1","showAs":"Functions"},{"value":"Fund","count":"1","showAs":"Fund"},{"value":"Fund/Funds","count":"5","showAs":"Fund / Funds"},{"value":"Funds","count":"2","showAs":"Funds"},{"value":"Game","count":"1","showAs":"Game"},{"value":"Gendarmerie","count":"1","showAs":"Gendarmerie"},{"value":"GenerationPlants","count":"1","showAs":"Generation Plants"},{"value":"Gestion","count":"1","showAs":"Gestion"},{"value":"Goods","count":"12","showAs":"Goods"},{"value":"Governance","count":"4","showAs":"Governance"},{"value":"Government","count":"22","showAs":"Government"},{"value":"GovernorInCouncil","count":"1","showAs":"Governor in Council"},{"value":"Gratuity","count":"1","showAs":"Gratuity"},{"value":"Guilty","count":"1","showAs":"Guilty"},{"value":"GunnyBags","count":"1","showAs":"Gunny Bags"},{"value":"Géométrique","count":"1","showAs":"Géométrique"},{"value":"HarbourSystem","count":"1","showAs":"Harbour system"},{"value":"Health","count":"1","showAs":"Health"},{"value":"Holiday","count":"1","showAs":"Holiday"},{"value":"Hospital","count":"1","showAs":"Hospital"},{"value":"Housing","count":"2","showAs":"Housing"},{"value":"Hunt","count":"1","showAs":"Hunt"},{"value":"Immunities","count":"1","showAs":"Immunities"},{"value":"Import","count":"5","showAs":"Import"},{"value":"Importation","count":"1","showAs":"Importation"},{"value":"Importations","count":"1","showAs":"Importations"},{"value":"Importer","count":"1","showAs":"Importer"},{"value":"Imprisonment","count":"4","showAs":"Imprisonment"},{"value":"Imputable","count":"1","showAs":"Imputable"},{"value":"Impôts","count":"1","showAs":"Impôts"},{"value":"Income","count":"1","showAs":"Income"},{"value":"Incorporation","count":"2","showAs":"Incorporation"},{"value":"Indemnites","count":"1","showAs":"Indemnites"},{"value":"Indemnité","count":"1","showAs":"Indemnité"},{"value":"Indemnités","count":"3","showAs":"Indemnités"},{"value":"IndustrialInjury","count":"1","showAs":"Industrial Injury"},{"value":"IndustrialRelations","count":"4","showAs":"Industrial Relations"},{"value":"Industrie","count":"1","showAs":"Industrie"},{"value":"Industry","count":"3","showAs":"Industry"},{"value":"Indémnite","count":"1","showAs":"Indémnite"},{"value":"Information","count":"3","showAs":"Information"},{"value":"InfrastructureDevelopment","count":"1","showAs":"Infrastructure Development"},{"value":"Inspector","count":"1","showAs":"Inspector"},{"value":"Institutions","count":"1","showAs":"Institutions"},{"value":"Instruction","count":"1","showAs":"Instruction"},{"value":"Insurance","count":"1","showAs":"Insurance"},{"value":"Integration","count":"1","showAs":"Integration"},{"value":"Interest","count":"1","showAs":"Interest"},{"value":"InternationalFinancialOrganisations","count":"1","showAs":"International Financial Organisations"},{"value":"InternationalLaw","count":"1","showAs":"International Law"},{"value":"Investment","count":"1","showAs":"Investment"},{"value":"Island","count":"1","showAs":"Island"},{"value":"Item","count":"1","showAs":"Item"},{"value":"Juges","count":"1","showAs":"Juges"},{"value":"Jurisdiction","count":"2","showAs":"Jurisdiction"},{"value":"Justice","count":"2","showAs":"Justice"},{"value":"Labour","count":"1","showAs":"Labour"},{"value":"LabourLaw","count":"6","showAs":"Labour Law"},{"value":"Latrines","count":"1","showAs":"Latrines"},{"value":"Legislative","count":"1","showAs":"Legislative"},{"value":"LegislativeAssembly","count":"1","showAs":"Legislative Assembly"},{"value":"LegislativeCouncil","count":"1","showAs":"Legislative Council"},{"value":"Liabilities","count":"1","showAs":"Liabilities"},{"value":"LiaisonOffice","count":"1","showAs":"Liaison Office"},{"value":"Licence","count":"6","showAs":"Licence"},{"value":"Licences","count":"2","showAs":"Licences"},{"value":"Licensing","count":"1","showAs":"Licensing"},{"value":"Liquidation","count":"1","showAs":"Liquidation"},{"value":"Loan","count":"1","showAs":"Loan"},{"value":"LoanScheme","count":"1","showAs":"Loan Scheme"},{"value":"LocalGovernment","count":"8","showAs":"Local Government"},{"value":"Loi","count":"1","showAs":"Loi"},{"value":"LowTideElevation","count":"1","showAs":"Low tide elevation"},{"value":"Magasin","count":"1","showAs":"Magasin"},{"value":"Maintenance","count":"1","showAs":"Maintenance"},{"value":"Mandat","count":"1","showAs":"Mandat"},{"value":"Manifestation","count":"1","showAs":"Manifestation"},{"value":"Manufacture","count":"1","showAs":"Manufacture"},{"value":"Marchandises","count":"2","showAs":"Marchandises"},{"value":"MarchésPublics","count":"1","showAs":"Marchés publics"},{"value":"Market","count":"1","showAs":"Market"},{"value":"Markets","count":"1","showAs":"Markets"},{"value":"Mausoleum","count":"1","showAs":"Mausoleum"},{"value":"MaximumPrice","count":"1","showAs":"Maximum Price"},{"value":"Medical","count":"1","showAs":"Medical"},{"value":"MedicalOfficer","count":"1","showAs":"Medical Officer"},{"value":"Membership","count":"1","showAs":"Membership"},{"value":"Menbrement","count":"1","showAs":"Menbrement"},{"value":"Mercuriales","count":"1","showAs":"Mercuriales"},{"value":"Militaire","count":"1","showAs":"Militaire"},{"value":"Militaires","count":"1","showAs":"Militaires"},{"value":"Miller","count":"1","showAs":"Miller"},{"value":"Minister","count":"10","showAs":"Minister"},{"value":"Modification","count":"3","showAs":"Modification"},{"value":"Moneylenders","count":"2","showAs":"Moneylenders"},{"value":"Montant","count":"1","showAs":"Montant"},{"value":"MotorVehicle","count":"1","showAs":"Motor vehicle"},{"value":"Municipal","count":"2","showAs":"Municipal"},{"value":"MunicipalCouncil","count":"1","showAs":"Municipal Council"},{"value":"Munitions","count":"1","showAs":"Munitions"},{"value":"Mécanique","count":"1","showAs":"Mécanique"},{"value":"NationalAssembly","count":"1","showAs":"National Assembly"},{"value":"NationalProductivity","count":"1","showAs":"National Productivity"},{"value":"NauticalMile","count":"1","showAs":"Nautical mile"},{"value":"Noise","count":"1","showAs":"Noise"},{"value":"Nomination","count":"1","showAs":"Nomination"},{"value":"Notice","count":"1","showAs":"Notice"},{"value":"Notification","count":"1","showAs":"Notification"},{"value":"NursingHomes","count":"1","showAs":"Nursing Homes"},{"value":"Oath","count":"1","showAs":"Oath"},{"value":"Obligation","count":"1","showAs":"Obligation"},{"value":"Obligation/Obligations","count":"1","showAs":"Obligation / Obligations"},{"value":"Obligations","count":"1","showAs":"Obligations"},{"value":"OccupationalHealth","count":"1","showAs":"Occupational Health"},{"value":"Offence","count":"3","showAs":"Offence"},{"value":"Offenders","count":"1","showAs":"Offenders"},{"value":"Officer","count":"1","showAs":"Officer"},{"value":"Offices","count":"1","showAs":"Offices"},{"value":"OfficialCorrespondence","count":"1","showAs":"Official Correspondence"},{"value":"Open","count":"1","showAs":"Open"},{"value":"Operation","count":"2","showAs":"Operation"},{"value":"Optiques","count":"1","showAs":"Optiques"},{"value":"Opérations","count":"2","showAs":"Opérations"},{"value":"Order","count":"23","showAs":"Order"},{"value":"Ordinance","count":"23","showAs":"Ordinance"},{"value":"Ordonnance","count":"2","showAs":"Ordonnance"},{"value":"Organisation","count":"5","showAs":"Organisation"},{"value":"Ouverture","count":"2","showAs":"Ouverture"},{"value":"PaidParking","count":"1","showAs":"Paid Parking"},{"value":"Parks","count":"1","showAs":"Parks"},{"value":"Parliament","count":"3","showAs":"Parliament"},{"value":"PartiPolitique","count":"1","showAs":"Parti politique"},{"value":"Participation","count":"1","showAs":"Participation"},{"value":"Passage","count":"1","showAs":"Passage"},{"value":"Passengers","count":"1","showAs":"Passengers"},{"value":"Patient","count":"1","showAs":"Patient"},{"value":"Payable","count":"1","showAs":"Payable"},{"value":"Payment","count":"1","showAs":"Payment"},{"value":"PedestrianCrossing","count":"1","showAs":"Pedestrian crossing"},{"value":"PenalServitude","count":"1","showAs":"Penal servitude"},{"value":"Pension","count":"4","showAs":"Pension"},{"value":"PensionCiviles","count":"1","showAs":"Pension civiles"},{"value":"PensionableOffices","count":"1","showAs":"Pensionable offices"},{"value":"PensionsOrdinance","count":"1","showAs":"Pensions Ordinance"},{"value":"People","count":"1","showAs":"People"},{"value":"PermanentSecretary","count":"1","showAs":"Permanent Secretary"},{"value":"Permit","count":"4","showAs":"Permit"},{"value":"Person/Persons","count":"2","showAs":"Person / Persons"},{"value":"PersonnalitéJuridique","count":"1","showAs":"Personnalité Juridique"},{"value":"Personnel","count":"1","showAs":"Personnel"},{"value":"PersonnesMorales","count":"1","showAs":"Personnes morales"},{"value":"Pesticides","count":"1","showAs":"Pesticides"},{"value":"Pharmacy","count":"1","showAs":"Pharmacy"},{"value":"Planning","count":"1","showAs":"Planning"},{"value":"Police","count":"5","showAs":"Police"},{"value":"Ports","count":"1","showAs":"Ports"},{"value":"Possession","count":"3","showAs":"Possession"},{"value":"PostOffice","count":"2","showAs":"Post Office"},{"value":"Postage","count":"1","showAs":"Postage"},{"value":"Pouvoirs","count":"1","showAs":"Pouvoirs"},{"value":"Powers","count":"1","showAs":"Powers"},{"value":"Practitioner","count":"1","showAs":"Practitioner"},{"value":"Prejudice","count":"1","showAs":"Prejudice"},{"value":"Premises","count":"2","showAs":"Premises"},{"value":"President","count":"3","showAs":"President"},{"value":"Prevention","count":"1","showAs":"Prevention"},{"value":"Price","count":"15","showAs":"Price"},{"value":"PrimeMinister","count":"1","showAs":"Prime Minister"},{"value":"PrivilegesAndImmunities","count":"1","showAs":"Privileges and Immunities"},{"value":"Probation","count":"1","showAs":"Probation"},{"value":"Procedure","count":"1","showAs":"Procedure"},{"value":"Proclamation","count":"13","showAs":"Proclamation"},{"value":"Produits","count":"1","showAs":"Produits"},{"value":"Professeurs","count":"1","showAs":"Professeurs"},{"value":"Profession","count":"2","showAs":"Profession"},{"value":"Professions","count":"1","showAs":"Professions"},{"value":"Prohibition","count":"1","showAs":"Prohibition"},{"value":"Promotion","count":"1","showAs":"Promotion"},{"value":"Promulgation","count":"5","showAs":"Promulgation"},{"value":"Property","count":"1","showAs":"Property"},{"value":"Proposition","count":"2","showAs":"Proposition"},{"value":"Prorogation","count":"1","showAs":"Prorogation"},{"value":"Prosecution","count":"1","showAs":"Prosecution"},{"value":"Protection","count":"8","showAs":"Protection"},{"value":"Provision","count":"2","showAs":"Provision"},{"value":"Prélèvement","count":"1","showAs":"Prélèvement"},{"value":"Public","count":"4","showAs":"Public"},{"value":"PublicHolidays","count":"3","showAs":"Public Holidays"},{"value":"PublicSafety","count":"1","showAs":"Public safety"},{"value":"PublicService","count":"2","showAs":"Public Service"},{"value":"Publication","count":"2","showAs":"Publication"},{"value":"Pupils","count":"1","showAs":"Pupils"},{"value":"Quarantine","count":"1","showAs":"Quarantine"},{"value":"Rates","count":"1","showAs":"Rates"},{"value":"Rationing","count":"1","showAs":"Rationing"},{"value":"Recherche","count":"1","showAs":"Recherche"},{"value":"Recruitment","count":"1","showAs":"Recruitment"},{"value":"Recrutement","count":"1","showAs":"Recrutement"},{"value":"Rectrument","count":"1","showAs":"Rectrument"},{"value":"ReflexionsStrategique","count":"1","showAs":"Reflexions strategique"},{"value":"ReformInstitution","count":"1","showAs":"Reform Institution"},{"value":"Registrar","count":"1","showAs":"Registrar"},{"value":"Registration","count":"3","showAs":"Registration"},{"value":"Regulation","count":"71","showAs":"Regulation"},{"value":"Regulations","count":"14","showAs":"Regulations"},{"value":"Reinsurance","count":"1","showAs":"Reinsurance"},{"value":"Relèvement","count":"1","showAs":"Relèvement"},{"value":"Remplacement","count":"1","showAs":"Remplacement"},{"value":"Remuneration","count":"8","showAs":"Remuneration"},{"value":"RemunerationOrder","count":"2","showAs":"Remuneration Order"},{"value":"Renewables","count":"1","showAs":"Renewables"},{"value":"Repeal","count":"11","showAs":"Repeal"},{"value":"Repealed","count":"1","showAs":"Repealed"},{"value":"Report","count":"1","showAs":"Report"},{"value":"Representation","count":"1","showAs":"Representation"},{"value":"Representative","count":"1","showAs":"Representative"},{"value":"Requête","count":"1","showAs":"Requête"},{"value":"Reserves","count":"1","showAs":"Reserves"},{"value":"Responsabilité","count":"1","showAs":"Responsabilité"},{"value":"Ressources","count":"1","showAs":"Ressources"},{"value":"Restrictions","count":"2","showAs":"Restrictions"},{"value":"Retirement","count":"1","showAs":"Retirement"},{"value":"RevenueAuthority","count":"1","showAs":"Revenue Authority"},{"value":"Revocation","count":"1","showAs":"Revocation"},{"value":"RoadHumps","count":"1","showAs":"Road Humps"},{"value":"RoadTraffic","count":"3","showAs":"Road Traffic"},{"value":"RoadTransport","count":"6","showAs":"Road Transport"},{"value":"Rules","count":"1","showAs":"Rules"},{"value":"Rum","count":"1","showAs":"Rum"},{"value":"Réduction","count":"1","showAs":"Réduction"},{"value":"Réglementation","count":"4","showAs":"Réglementation"},{"value":"Rémunération","count":"1","showAs":"Rémunération"},{"value":"Réorganisation","count":"4","showAs":"Réorganisation"},{"value":"Répartition","count":"1","showAs":"Répartition"},{"value":"RéserveGénérale","count":"1","showAs":"Réserve générale"},{"value":"Salary","count":"2","showAs":"Salary"},{"value":"Sale","count":"9","showAs":"Sale"},{"value":"Sanction","count":"1","showAs":"Sanction"},{"value":"Sanitary","count":"1","showAs":"Sanitary"},{"value":"Santé","count":"1","showAs":"Santé"},{"value":"SantéPublique","count":"1","showAs":"Santé publique"},{"value":"Savings","count":"1","showAs":"Savings"},{"value":"Scholarships","count":"1","showAs":"Scholarships"},{"value":"SecuriteDeL'emploi","count":"1","showAs":"Securite de l'emploi"},{"value":"SecurityCouncil","count":"1","showAs":"Security Council"},{"value":"Service","count":"12","showAs":"Service"},{"value":"Services","count":"1","showAs":"Services"},{"value":"Session","count":"1","showAs":"Session"},{"value":"Ship","count":"1","showAs":"Ship"},{"value":"Shipping","count":"2","showAs":"Shipping"},{"value":"Siège","count":"1","showAs":"Siège"},{"value":"SmallEnterprises","count":"1","showAs":"Small Enterprises"},{"value":"SocialAId","count":"1","showAs":"Social AId"},{"value":"Solde","count":"2","showAs":"Solde"},{"value":"Somme","count":"3","showAs":"Somme"},{"value":"Specification","count":"1","showAs":"Specification"},{"value":"SportLaw","count":"3","showAs":"Sport Law"},{"value":"Spécialisation","count":"1","showAs":"Spécialisation"},{"value":"Stadium","count":"1","showAs":"Stadium"},{"value":"Stallholder","count":"1","showAs":"Stallholder"},{"value":"Stands","count":"1","showAs":"Stands"},{"value":"State","count":"1","showAs":"State"},{"value":"Statement","count":"1","showAs":"Statement"},{"value":"Statistics","count":"3","showAs":"Statistics"},{"value":"Statut","count":"1","showAs":"Statut"},{"value":"StatutoryBodies","count":"1","showAs":"Statutory Bodies"},{"value":"Street","count":"1","showAs":"Street"},{"value":"Sugar","count":"2","showAs":"Sugar"},{"value":"SugarIndustry","count":"1","showAs":"Sugar Industry"},{"value":"SugarWorkers","count":"1","showAs":"Sugar workers"},{"value":"SummerTime","count":"1","showAs":"Summer Time"},{"value":"Supervision","count":"1","showAs":"Supervision"},{"value":"Supplies","count":"7","showAs":"Supplies"},{"value":"SuppliesControlAct","count":"1","showAs":"Supplies Control Act"},{"value":"Supply","count":"6","showAs":"Supply"},{"value":"Surgeon","count":"1","showAs":"Surgeon"},{"value":"Survey","count":"1","showAs":"Survey"},{"value":"Suspension","count":"2","showAs":"Suspension"},{"value":"Tariff","count":"2","showAs":"Tariff"},{"value":"Taux","count":"2","showAs":"Taux"},{"value":"Tax","count":"10","showAs":"Tax"},{"value":"Taxe","count":"1","showAs":"Taxe"},{"value":"Telecommunications","count":"2","showAs":"Telecommunications"},{"value":"Temps","count":"1","showAs":"Temps"},{"value":"TerminalExpansionFee","count":"1","showAs":"Terminal Expansion Fee"},{"value":"Titulaire","count":"1","showAs":"Titulaire"},{"value":"Trades","count":"1","showAs":"Trades"},{"value":"TraditionalMedicine","count":"1","showAs":"Traditional Medicine"},{"value":"Traffic","count":"6","showAs":"Traffic"},{"value":"TrafficSign","count":"1","showAs":"Traffic sign"},{"value":"Train","count":"1","showAs":"Train"},{"value":"Training","count":"1","showAs":"Training"},{"value":"Traitements","count":"2","showAs":"Traitements"},{"value":"Traités","count":"1","showAs":"Traités"},{"value":"Transition","count":"1","showAs":"Transition"},{"value":"Transport","count":"5","showAs":"Transport"},{"value":"TravauxNeufs","count":"1","showAs":"Travaux neufs"},{"value":"TravauxPublics","count":"3","showAs":"Travaux publics"},{"value":"Treatment","count":"1","showAs":"Treatment"},{"value":"Treaty/Treaties","count":"1","showAs":"Treaty / Treaties"},{"value":"Tribunal","count":"1","showAs":"Tribunal"},{"value":"Trésorerie","count":"1","showAs":"Trésorerie"},{"value":"Trésorier","count":"1","showAs":"Trésorier"},{"value":"Télécommunications","count":"2","showAs":"Télécommunications"},{"value":"UN-UnitedNations","count":"1","showAs":"UN - United Nations"},{"value":"Unemployment","count":"1","showAs":"Unemployment"},{"value":"Universités","count":"1","showAs":"Universités"},{"value":"Utilities","count":"1","showAs":"Utilities"},{"value":"VAT","count":"1","showAs":"VAT"},{"value":"Valuation","count":"1","showAs":"Valuation"},{"value":"Ventilation","count":"1","showAs":"Ventilation"},{"value":"Versement","count":"1","showAs":"Versement"},{"value":"Viande","count":"1","showAs":"Viande"},{"value":"VicePresident","count":"1","showAs":"Vice President"},{"value":"Village","count":"1","showAs":"Village"},{"value":"Véhicules","count":"1","showAs":"Véhicules"},{"value":"Wages","count":"2","showAs":"Wages"},{"value":"Welfare","count":"2","showAs":"Welfare"},{"value":"Wharf","count":"1","showAs":"Wharf"},{"value":"Wildlife","count":"1","showAs":"Wildlife"},{"value":"Workers","count":"4","showAs":"Workers"},{"value":"Youth/YoungPeople","count":"2","showAs":"Youth / Young People"},{"value":"authority","count":"21","showAs":"authority"},{"value":"chômage","count":"1","showAs":"chômage"},{"value":"contract","count":"3","showAs":"contract"},{"value":"corruption","count":"1","showAs":"corruption"},{"value":"creditors","count":"1","showAs":"creditors"},{"value":"crime","count":"2","showAs":"crime"},{"value":"decision","count":"1","showAs":"decision"},{"value":"development","count":"2","showAs":"development"},{"value":"education","count":"3","showAs":"education"},{"value":"employees","count":"1","showAs":"employees"},{"value":"environment","count":"3","showAs":"environment"},{"value":"health","count":"3","showAs":"health"},{"value":"indemnité","count":"1","showAs":"indemnité"},{"value":"industry","count":"1","showAs":"industry"},{"value":"law","count":"1","showAs":"law"},{"value":"liability","count":"4","showAs":"liability"},{"value":"license","count":"1","showAs":"license"},{"value":"liquidator","count":"1","showAs":"liquidator"},{"value":"management","count":"2","showAs":"management"},{"value":"marriage","count":"1","showAs":"marriage"},{"value":"media","count":"1","showAs":"media"},{"value":"offence","count":"1","showAs":"offence"},{"value":"passenger","count":"1","showAs":"passenger"},{"value":"possession","count":"1","showAs":"possession"},{"value":"proclamation","count":"1","showAs":"proclamation"},{"value":"programmation","count":"1","showAs":"programmation"},{"value":"property","count":"3","showAs":"property"},{"value":"rehabilitation","count":"1","showAs":"rehabilitation"},{"value":"risks","count":"1","showAs":"risks"},{"value":"security","count":"1","showAs":"security"},{"value":"stock","count":"1","showAs":"stock"},{"value":"sugar","count":"1","showAs":"sugar"},{"value":"trade","count":"13","showAs":"trade"},{"value":"Électriques","count":"1","showAs":"Électriques"},{"value":"Érection","count":"1","showAs":"Érection"}]}]}